{"mean":{"confidence_interval":{"confidence_level":0.95,"lower_bound":60723.936884778515,"upper_bound":61339.0943137785},"point_estimate":61017.54145100467,"standard_error":157.06505159271512},"median":{"confidence_interval":{"confidence_level":0.95,"lower_bound":60773.986767120645,"upper_bound":61078.84056389013},"point_estimate":60936.656314142034,"standard_error":88.89878134356421},"median_abs_dev":{"confidence_interval":{"confidence_level":0.95,"lower_bound":217.38179480840847,"upper_bound":958.8536040257947},"point_estimate":611.1336736329675,"standard_error":182.6170109681356},"slope":{"confidence_interval":{"confidence_level":0.95,"lower_bound":60609.433433087484,"upper_bound":61140.01322685625},"point_estimate":60864.61439000225,"standard_error":135.6617528029088},"std_dev":{"confidence_interval":{"confidence_level":0.95,"lower_bound":533.7671890818687,"upper_bound":1128.0851179073738},"point_estimate":869.8012168579381,"standard_error":152.72973114442968}}