{"mean":{"confidence_interval":{"confidence_level":0.95,"lower_bound":31354.31230809575,"upper_bound":31906.97891844093},"point_estimate":31619.12831109475,"standard_error":141.52532296268956},"median":{"confidence_interval":{"confidence_level":0.95,"lower_bound":31247.172773103848,"upper_bound":31850.26268137979},"point_estimate":31520.0882501778,"standard_error":174.07958575766256},"median_abs_dev":{"confidence_interval":{"confidence_level":0.95,"lower_bound":375.5922600784716,"upper_bound":946.8123306712497},"point_estimate":646.8694100912224,"standard_error":147.2968181006207},"slope":{"confidence_interval":{"confidence_level":0.95,"lower_bound":31362.497655725372,"upper_bound":31830.884909934346},"point_estimate":31589.00075644017,"standard_error":119.75045195210335},"std_dev":{"confidence_interval":{"confidence_level":0.95,"lower_bound":504.4882068313244,"upper_bound":1036.5787821780598},"point_estimate":787.3391940949114,"standard_error":140.46037598580511}}